setup.py
my_first_ever_python_package/Binomialdistribution.py
my_first_ever_python_package/Gaussiandistribution.py
my_first_ever_python_package/Generaldistribution.py
my_first_ever_python_package/__init__.py
my_first_ever_python_package.egg-info/PKG-INFO
my_first_ever_python_package.egg-info/SOURCES.txt
my_first_ever_python_package.egg-info/dependency_links.txt
my_first_ever_python_package.egg-info/not-zip-safe
my_first_ever_python_package.egg-info/top_level.txt