Metadata-Version: 1.0
Name: my-first-ever-python-package
Version: 1.1
Summary: Gaussian and Binomial distributions
Home-page: UNKNOWN
Author: Nabanita Ganguly
Author-email: nabanita.rimpi@gmail.com
License: UNKNOWN
Platform: UNKNOWN
